cyndilib-0.1.0.dist-info/RECORD
cyndilib-0.1.0.dist-info/WHEEL
cyndilib-0.1.0.dist-info/top_level.txt
cyndilib-0.1.0.dist-info/METADATA
cyndilib-0.1.0.dist-info/licenses/LICENSE
cyndilib-0.1.0.dist-info/licenses/libndi_licenses.txt
cyndilib/framesync_helper.pxd
cyndilib/audio_reference.pxd
cyndilib/locks.pyx
cyndilib/sender.cpp
cyndilib/metadata_frame.pyx
cyndilib/sender.pxd
cyndilib/finder.cpython-313-darwin.so
cyndilib/audio_reference.cpp
cyndilib/audio_frame.cpp
cyndilib/buffertypes.pyx
cyndilib/callback.cpp
cyndilib/finder.pyx
cyndilib/callback.pxd
cyndilib/audio_frame.pxd
cyndilib/audio_frame.pyi
cyndilib/sender.cpython-313-darwin.so
cyndilib/__init__.pxd
cyndilib/metadata_frame.cpython-313-darwin.so
cyndilib/callback.pyi
cyndilib/locks.cpython-313-darwin.so
cyndilib/send_frame_status.pyx
cyndilib/__init__.py
cyndilib/video_frame.pyx
cyndilib/framesync.pyx
cyndilib/sender.pyi
cyndilib/receiver.pyx
cyndilib/audio_reference.pyi
cyndilib/clock.pxd
cyndilib/audio_frame.cpython-313-darwin.so
cyndilib/locks.pyi
cyndilib/send_frame_status.cpython-313-darwin.so
cyndilib/framesync.cpp
cyndilib/video_frame.cpp
cyndilib/receiver.cpp
cyndilib/framesync.pxd
cyndilib/video_frame.pxd
cyndilib/receiver.pxd
cyndilib/send_frame_status.pxd
cyndilib/finder.pyi
cyndilib/audio_reference.cpython-313-darwin.so
cyndilib/video_frame.cpython-313-darwin.so
cyndilib/send_frame_status.cpp
cyndilib/audio_frame.pyx
cyndilib/callback.cpython-313-darwin.so
cyndilib/callback.pyx
cyndilib/buffertypes.cpp
cyndilib/finder.cpp
cyndilib/receiver.cpython-313-darwin.so
cyndilib/buffertypes.pxd
cyndilib/finder.pxd
cyndilib/locks.cpp
cyndilib/receiver.pyi
cyndilib/video_frame.pyi
cyndilib/metadata_frame.cpp
cyndilib/framesync.pyi
cyndilib/sender.pyx
cyndilib/metadata_frame.pxd
cyndilib/framesync.cpython-313-darwin.so
cyndilib/buffertypes.cpython-313-darwin.so
cyndilib/audio_reference.pyx
cyndilib/locks.pxd
cyndilib/wrapper/types.pxd
cyndilib/wrapper/ndi_recv.cpython-313-darwin.so
cyndilib/wrapper/common.pxd
cyndilib/wrapper/ndi_structs.pyx
cyndilib/wrapper/common.cpp
cyndilib/wrapper/ndi_find.pxd
cyndilib/wrapper/ndi_framesync.pxd
cyndilib/wrapper/ndi_recv.pyx
