Metadata-Version: 2.4
Name: cyndilib
Version: 0.1.0
Summary: Python wrapper for NDI® written in Cython
Author-email: Matthew Reid <matt@nomadic-recording.com>
License-Expression: MIT
Project-URL: Homepage, https://github.com/nocarryr/cyndilib
Project-URL: Documentation, https://cyndilib.readthedocs.io
Project-URL: Download, https://pypi.org/project/cyndilib
Project-URL: Source, https://github.com/nocarryr/cyndilib
Project-URL: Tracker, https://github.com/nocarryr/cyndilib/issues
Classifier: Development Status :: 3 - Alpha
Classifier: Intended Audience :: Developers
Classifier: Natural Language :: English
Classifier: Operating System :: MacOS
Classifier: Operating System :: MacOS :: MacOS X
Classifier: Operating System :: Microsoft
Classifier: Operating System :: Microsoft :: Windows
Classifier: Operating System :: Microsoft :: Windows :: Windows 10
Classifier: Operating System :: POSIX
Classifier: Operating System :: POSIX :: Linux
Classifier: Programming Language :: Cython
Classifier: Programming Language :: Python
Classifier: Programming Language :: Python :: 3 :: Only
Classifier: Programming Language :: Python :: 3.10
Classifier: Programming Language :: Python :: 3.11
Classifier: Programming Language :: Python :: 3.12
Classifier: Programming Language :: Python :: 3.13
Classifier: Programming Language :: Python :: 3.14
Classifier: Programming Language :: Python :: Implementation :: CPython
Classifier: Topic :: Multimedia
Classifier: Topic :: Multimedia :: Sound/Audio
Classifier: Topic :: Multimedia :: Sound/Audio :: Capture/Recording
Classifier: Topic :: Multimedia :: Sound/Audio :: Conversion
Classifier: Topic :: Multimedia :: Video
Classifier: Topic :: Multimedia :: Video :: Capture
Classifier: Topic :: Multimedia :: Video :: Conversion
Classifier: Topic :: Software Development
Classifier: Topic :: Software Development :: Libraries
Classifier: Topic :: Software Development :: Libraries :: Python Modules
Requires-Python: >=3.10
License-File: LICENSE
License-File: libndi_licenses.txt
Requires-Dist: numpy
Requires-Dist: importlib_resources; python_version < "3.9"
Dynamic: license-file
